.gitignore
.travis.yml
LICENSE.txt
MANIFEST.in
NOTICE.txt
README.rst
requirements.txt
setup.cfg
setup.py
docs/Makefile
docs/source/conf.py
docs/source/faq.rst
docs/source/index.rst
docs/source/installing.rst
docs/source/tutorial.rst
docs/source/api/index.rst
docs/source/exmples/index.rst
src/livetribe/__init__.py
src/livetribe/plugins.py
src/livetribe_plugins.egg-info/PKG-INFO
src/livetribe_plugins.egg-info/SOURCES.txt
src/livetribe_plugins.egg-info/dependency_links.txt
src/livetribe_plugins.egg-info/namespace_packages.txt
src/livetribe_plugins.egg-info/not-zip-safe
src/livetribe_plugins.egg-info/top_level.txt
tests/test_plugins.py
tests/acme/__init__.py
tests/acme/framework/__init__.py
tests/acme/framework/factory.py
tests/acme/plugins/__init__.py
tests/acme/plugins/mock/__init__.py
tests/acme/plugins/mock/factory.py
tests/acme/plugins/mock/submodule/__init__.py
tests/acme/plugins/mock/submodule/factory.py