Metadata-Version: 1.0
Name: livetribe-plugins
Version: 1.0a1
Summary: A simple Python plugin framework.
Home-page: http://github.com/livetribe/livetribe-plugins/
Author: Alan D. Cabrera
Author-email: dev@livetribe.codehaus.org
License: Apache Software License (http://www.apache.org/licenses/LICENSE-2.0)
Platform: any
Classifier: Intended Audience :: Developers
Classifier: Intended Audience :: System Administrators
Classifier: License :: OSI Approved :: Apache Software License
Classifier: Operating System :: OS Independent
Classifier: Programming Language :: Python
Classifier: Programming Language :: Python :: 2.6
Classifier: Programming Language :: Python :: 2.7
Classifier: Programming Language :: Python :: 3.2
Classifier: Programming Language :: Python :: 3.3
Classifier: Topic :: Software Development :: Libraries :: Python Modules
